{
  "0": {
    "basicblocks": 1,
    "calls": "24 20 41 31 21 1 42 10 12 22",
    "file": "myproject.cpp",
    "fileloc": 7,
    "instructions": 59,
    "name": "myproject",
    "total_instructions": 3105
  },
  "1": {
    "basicblocks": 5,
    "calls": "35",
    "file": "nnet_conv2d_stream.h",
    "fileloc": 66,
    "instructions": 34,
    "name": "conv_2d_cl<nnet::array<ap_ufixed<6, 0, AP_RND_CONV, AP_SAT, 0>, 4>, nnet::array<ap_fixed<20, 10, AP_TRN, AP_WRAP, 0>, 5>, config9>",
    "stores": {
      "L": 4
    },
    "total_instructions": 735
  },
  "10": {
    "basicblocks": 5,
    "calls": "7",
    "file": "nnet_conv2d_stream.h",
    "fileloc": 66,
    "instructions": 37,
    "name": "conv_2d_cl<nnet::array<ap_ufixed<6, 0, AP_RND_CONV, AP_SAT, 0>, 5>, nnet::array<ap_fixed<19, 9, AP_TRN, AP_WRAP, 0>, 6>, config12>",
    "stores": {
      "L": 5
    },
    "total_instructions": 489
  },
  "11": {
    "basicblocks": 1,
    "calls": "",
    "file": "nnet_types.h",
    "fileloc": 17,
    "instructions": 2,
    "name": "operator[]",
    "total_instructions": 2
  },
  "12": {
    "basicblocks": 33,
    "calls": "27 6 6 27 6 6 27 6 6 27 6 6 27 6 6 27 6 6",
    "file": "nnet_activation_stream.h",
    "fileloc": 39,
    "instructions": 330,
    "loads": {
      "L": 12
    },
    "name": "relu<nnet::array<ap_fixed<19, 9, AP_TRN, AP_WRAP, 0>, 6>, nnet::array<ap_ufixed<6, 0, AP_RND_CONV, AP_SAT, 0>, 6>, relu_config14>",
    "stores": {
      "L": 18
    },
    "total_instructions": 366
  },
  "13": {
    "basicblocks": 1,
    "calls": "",
    "file": "nnet_types.h",
    "fileloc": 17,
    "instructions": 2,
    "name": "operator[]",
    "total_instructions": 2
  },
  "14": {
    "basicblocks": 1,
    "calls": "",
    "file": "nnet_types.h",
    "fileloc": 19,
    "instructions": 2,
    "name": "operator[]",
    "total_instructions": 2
  },
  "15": {
    "basicblocks": 15,
    "calls": "32 32 32 32 32 32",
    "file": "nnet_dense_resource.h",
    "fileloc": 13,
    "instructions": 188,
    "loads": {
      "G": 7,
      "L": 12
    },
    "name": "dense_resource_rf_leq_nin<ap_ufixed<6, 0, AP_RND_CONV, AP_SAT, 0>, ap_fixed<19, 9, AP_TRN, AP_WRAP, 0>, config12_mult>",
    "stores": {
      "L": 24
    },
    "total_instructions": 200
  },
  "16": {
    "basicblocks": 1,
    "calls": "28 28",
    "file": "nnet_conv_stream.h",
    "fileloc": 215,
    "instructions": 125,
    "loads": {
      "G": 40,
      "L": 2
    },
    "name": "shift_line_buffer<nnet::array<ap_ufixed<6, 0, AP_RND_CONV, AP_SAT, 0>, 2>, config6>",
    "stores": {
      "G": 50
    },
    "total_instructions": 129
  },
  "17": {
    "basicblocks": 1,
    "calls": "",
    "file": "nnet_types.h",
    "fileloc": 17,
    "instructions": 2,
    "name": "operator[]",
    "total_instructions": 2
  },
  "18": {
    "basicblocks": 1,
    "calls": "",
    "file": "nnet_types.h",
    "fileloc": 19,
    "instructions": 2,
    "name": "operator[]",
    "total_instructions": 2
  },
  "19": {
    "basicblocks": 1,
    "calls": "18",
    "file": "nnet_conv_stream.h",
    "fileloc": 215,
    "instructions": 64,
    "loads": {
      "G": 20,
      "L": 1
    },
    "name": "shift_line_buffer<nnet::array<ap_fixed<8, 1, AP_RND_CONV, AP_SAT, 0>, 1>, config3>",
    "stores": {
      "G": 25
    },
    "total_instructions": 66
  },
  "2": {
    "basicblocks": 1,
    "calls": "25 25 25 25 25",
    "file": "nnet_conv_stream.h",
    "fileloc": 215,
    "instructions": 128,
    "loads": {
      "G": 30,
      "L": 5
    },
    "name": "shift_line_buffer<nnet::array<ap_ufixed<6, 0, AP_RND_CONV, AP_SAT, 0>, 5>, config12>",
    "stores": {
      "G": 45
    },
    "total_instructions": 138
  },
  "20": {
    "basicblocks": 5,
    "calls": "40",
    "file": "nnet_conv2d_stream.h",
    "fileloc": 66,
    "instructions": 24,
    "name": "conv_2d_cl<nnet::array<ap_fixed<8, 1, AP_RND_CONV, AP_SAT, 0>, 1>, nnet::array<ap_fixed<20, 9, AP_TRN, AP_WRAP, 0>, 2>, config3>",
    "stores": {
      "L": 1
    },
    "total_instructions": 232
  },
  "21": {
    "basicblocks": 23,
    "calls": "38 9 9 38 9 9 38 9 9 38 9 9",
    "file": "nnet_activation_stream.h",
    "fileloc": 39,
    "instructions": 226,
    "loads": {
      "L": 8
    },
    "name": "relu<nnet::array<ap_fixed<19, 9, AP_TRN, AP_WRAP, 0>, 4>, nnet::array<ap_ufixed<6, 0, AP_RND_CONV, AP_SAT, 0>, 4>, relu_config8>",
    "stores": {
      "L": 12
    },
    "total_instructions": 250
  },
  "22": {
    "basicblocks": 3,
    "calls": "4",
    "file": "nnet_dense_stream.h",
    "fileloc": 82,
    "instructions": 53,
    "loads": {
      "L": 1
    },
    "name": "dense<nnet::array<ap_ufixed<6, 0, AP_RND_CONV, AP_SAT, 0>, 6>, nnet::array<ap_fixed<16, 6, AP_TRN, AP_WRAP, 0>, 1>, config16>",
    "stores": {
      "L": 6
    },
    "total_instructions": 99
  },
  "23": {
    "basicblocks": 1,
    "calls": "",
    "file": "nnet_mult.h",
    "fileloc": 110,
    "instructions": 2,
    "name": "cast<ap_ufixed<6, 0, AP_RND_CONV, AP_SAT, 0>, ap_fixed<20, 10, AP_TRN, AP_WRAP, 0>, config9_mult>",
    "stores": {
      "L": 1
    },
    "total_instructions": 2
  },
  "24": {
    "basicblocks": 3,
    "calls": "37 11",
    "file": "nnet_activation_stream.h",
    "fileloc": 17,
    "instructions": 38,
    "loads": {
      "L": 2
    },
    "name": "linear<nnet::array<ap_uint<8>, 1>, nnet::array<ap_fixed<8, 1, AP_RND_CONV, AP_SAT, 0>, 1>, linear_config2>",
    "stores": {
      "L": 2
    },
    "total_instructions": 42
  },
  "25": {
    "basicblocks": 1,
    "calls": "",
    "file": "nnet_types.h",
    "fileloc": 19,
    "instructions": 2,
    "name": "operator[]",
    "total_instructions": 2
  },
  "26": {
    "basicblocks": 10,
    "calls": "16 3 38 38 38 38",
    "file": "nnet_conv_stream.h",
    "fileloc": 251,
    "instructions": 88,
    "loads": {
      "G": 8,
      "L": 8
    },
    "name": "compute_output_buffer_2d<nnet::array<ap_ufixed<6, 0, AP_RND_CONV, AP_SAT, 0>, 2>, nnet::array<ap_fixed<19, 9, AP_TRN, AP_WRAP, 0>, 4>, config6>",
    "stores": {
      "G": 7,
      "L": 4
    },
    "total_instructions": 363
  },
  "27": {
    "basicblocks": 1,
    "calls": "",
    "file": "nnet_types.h",
    "fileloc": 17,
    "instructions": 2,
    "name": "operator[]",
    "total_instructions": 2
  },
  "28": {
    "basicblocks": 1,
    "calls": "",
    "file": "nnet_types.h",
    "fileloc": 19,
    "instructions": 2,
    "name": "operator[]",
    "total_instructions": 2
  },
  "29": {
    "basicblocks": 1,
    "calls": "",
    "file": "nnet_types.h",
    "fileloc": 17,
    "instructions": 2,
    "name": "operator[]",
    "total_instructions": 2
  },
  "3": {
    "basicblocks": 11,
    "calls": "36 36 36 36",
    "file": "nnet_dense_resource.h",
    "fileloc": 13,
    "instructions": 130,
    "loads": {
      "G": 5,
      "L": 8
    },
    "name": "dense_resource_rf_leq_nin<ap_ufixed<6, 0, AP_RND_CONV, AP_SAT, 0>, ap_fixed<19, 9, AP_TRN, AP_WRAP, 0>, config6_mult>",
    "stores": {
      "L": 16
    },
    "total_instructions": 138
  },
  "30": {
    "basicblocks": 1,
    "calls": "",
    "file": "nnet_types.h",
    "fileloc": 17,
    "instructions": 2,
    "name": "operator[]",
    "total_instructions": 2
  },
  "31": {
    "basicblocks": 5,
    "calls": "26",
    "file": "nnet_conv2d_stream.h",
    "fileloc": 66,
    "instructions": 28,
    "name": "conv_2d_cl<nnet::array<ap_ufixed<6, 0, AP_RND_CONV, AP_SAT, 0>, 2>, nnet::array<ap_fixed<19, 9, AP_TRN, AP_WRAP, 0>, 4>, config6>",
    "stores": {
      "L": 2
    },
    "total_instructions": 391
  },
  "32": {
    "basicblocks": 1,
    "calls": "",
    "file": "nnet_mult.h",
    "fileloc": 110,
    "instructions": 2,
    "name": "cast<ap_ufixed<6, 0, AP_RND_CONV, AP_SAT, 0>, ap_fixed<19, 9, AP_TRN, AP_WRAP, 0>, config12_mult>",
    "stores": {
      "L": 1
    },
    "total_instructions": 2
  },
  "33": {
    "basicblocks": 1,
    "calls": "",
    "file": "nnet_mult.h",
    "fileloc": 110,
    "instructions": 3,
    "name": "cast<ap_ufixed<6, 0, AP_RND_CONV, AP_SAT, 0>, ap_fixed<16, 6, AP_TRN, AP_WRAP, 0>, config16>",
    "stores": {
      "L": 1
    },
    "total_instructions": 3
  },
  "34": {
    "basicblocks": 1,
    "calls": "14 14 14 14",
    "file": "nnet_conv_stream.h",
    "fileloc": 215,
    "instructions": 247,
    "loads": {
      "G": 80,
      "L": 4
    },
    "name": "shift_line_buffer<nnet::array<ap_ufixed<6, 0, AP_RND_CONV, AP_SAT, 0>, 4>, config9>",
    "stores": {
      "G": 100
    },
    "total_instructions": 255
  },
  "35": {
    "basicblocks": 10,
    "calls": "34 39 17 17 17 17 17",
    "file": "nnet_conv_stream.h",
    "fileloc": 251,
    "instructions": 96,
    "loads": {
      "G": 8,
      "L": 10
    },
    "name": "compute_output_buffer_2d<nnet::array<ap_ufixed<6, 0, AP_RND_CONV, AP_SAT, 0>, 4>, nnet::array<ap_fixed<20, 10, AP_TRN, AP_WRAP, 0>, 5>, config9>",
    "stores": {
      "G": 7,
      "L": 5
    },
    "total_instructions": 701
  },
  "36": {
    "basicblocks": 1,
    "calls": "",
    "file": "nnet_mult.h",
    "fileloc": 110,
    "instructions": 2,
    "name": "cast<ap_ufixed<6, 0, AP_RND_CONV, AP_SAT, 0>, ap_fixed<19, 9, AP_TRN, AP_WRAP, 0>, config6_mult>",
    "stores": {
      "L": 1
    },
    "total_instructions": 2
  },
  "37": {
    "basicblocks": 1,
    "calls": "",
    "file": "nnet_types.h",
    "fileloc": 17,
    "instructions": 2,
    "name": "operator[]",
    "total_instructions": 2
  },
  "38": {
    "basicblocks": 1,
    "calls": "",
    "file": "nnet_types.h",
    "fileloc": 17,
    "instructions": 2,
    "name": "operator[]",
    "total_instructions": 2
  },
  "39": {
    "basicblocks": 23,
    "calls": "23 23 23 23 23",
    "file": "nnet_dense_resource.h",
    "fileloc": 13,
    "instructions": 330,
    "loads": {
      "G": 20,
      "L": 10
    },
    "name": "dense_resource_rf_leq_nin<ap_ufixed<6, 0, AP_RND_CONV, AP_SAT, 0>, ap_fixed<20, 10, AP_TRN, AP_WRAP, 0>, config9_mult>",
    "stores": {
      "L": 30
    },
    "total_instructions": 340
  },
  "4": {
    "basicblocks": 5,
    "calls": "33",
    "file": "nnet_dense_resource.h",
    "fileloc": 13,
    "instructions": 43,
    "loads": {
      "G": 1,
      "L": 3
    },
    "name": "dense_resource_rf_leq_nin<ap_ufixed<6, 0, AP_RND_CONV, AP_SAT, 0>, ap_fixed<16, 6, AP_TRN, AP_WRAP, 0>, config16>",
    "stores": {
      "L": 4
    },
    "total_instructions": 46
  },
  "40": {
    "basicblocks": 10,
    "calls": "19 5 30 30",
    "file": "nnet_conv_stream.h",
    "fileloc": 251,
    "instructions": 72,
    "loads": {
      "G": 8,
      "L": 4
    },
    "name": "compute_output_buffer_2d<nnet::array<ap_fixed<8, 1, AP_RND_CONV, AP_SAT, 0>, 1>, nnet::array<ap_fixed<20, 9, AP_TRN, AP_WRAP, 0>, 2>, config3>",
    "stores": {
      "G": 7,
      "L": 2
    },
    "total_instructions": 208
  },
  "41": {
    "basicblocks": 13,
    "calls": "30 13 13 30 13 13",
    "file": "nnet_activation_stream.h",
    "fileloc": 39,
    "instructions": 122,
    "loads": {
      "L": 4
    },
    "name": "relu<nnet::array<ap_fixed<20, 9, AP_TRN, AP_WRAP, 0>, 2>, nnet::array<ap_ufixed<6, 0, AP_RND_CONV, AP_SAT, 0>, 2>, relu_config5>",
    "stores": {
      "L": 6
    },
    "total_instructions": 134
  },
  "42": {
    "basicblocks": 28,
    "calls": "17 29 29 17 29 29 17 29 29 17 29 29 17 29 29",
    "file": "nnet_activation_stream.h",
    "fileloc": 39,
    "instructions": 278,
    "loads": {
      "L": 10
    },
    "name": "relu<nnet::array<ap_fixed<20, 10, AP_TRN, AP_WRAP, 0>, 5>, nnet::array<ap_ufixed<6, 0, AP_RND_CONV, AP_SAT, 0>, 5>, relu_config11>",
    "stores": {
      "L": 15
    },
    "total_instructions": 308
  },
  "5": {
    "basicblocks": 5,
    "calls": "8 8",
    "file": "nnet_dense_resource.h",
    "fileloc": 87,
    "instructions": 62,
    "loads": {
      "G": 3,
      "L": 5
    },
    "name": "dense_resource_rf_gt_nin_rem0<ap_fixed<8, 1, AP_RND_CONV, AP_SAT, 0>, ap_fixed<20, 9, AP_TRN, AP_WRAP, 0>, config3_mult>",
    "stores": {
      "L": 6
    },
    "total_instructions": 66
  },
  "6": {
    "basicblocks": 1,
    "calls": "",
    "file": "nnet_types.h",
    "fileloc": 17,
    "instructions": 2,
    "name": "operator[]",
    "total_instructions": 2
  },
  "7": {
    "basicblocks": 10,
    "calls": "2 15 27 27 27 27 27 27",
    "file": "nnet_conv_stream.h",
    "fileloc": 251,
    "instructions": 102,
    "loads": {
      "G": 8,
      "L": 12
    },
    "name": "compute_output_buffer_2d<nnet::array<ap_ufixed<6, 0, AP_RND_CONV, AP_SAT, 0>, 5>, nnet::array<ap_fixed<19, 9, AP_TRN, AP_WRAP, 0>, 6>, config12>",
    "stores": {
      "G": 7,
      "L": 6
    },
    "total_instructions": 452
  },
  "8": {
    "basicblocks": 1,
    "calls": "",
    "file": "nnet_mult.h",
    "fileloc": 110,
    "instructions": 2,
    "name": "cast<ap_fixed<8, 1, AP_RND_CONV, AP_SAT, 0>, ap_fixed<20, 9, AP_TRN, AP_WRAP, 0>, config3_mult>",
    "stores": {
      "L": 1
    },
    "total_instructions": 2
  },
  "9": {
    "basicblocks": 1,
    "calls": "",
    "file": "nnet_types.h",
    "fileloc": 17,
    "instructions": 2,
    "name": "operator[]",
    "total_instructions": 2
  }
}