{
  "ConvolutionInputGenerator_rtl_0": {},
  "MVAU_hls_0": {
    "op_mac_4bx8b": 540000,
    "param_weight_4b": 600,
    "param_threshold_16b": 24
  },
  "ConvolutionInputGenerator_rtl_1": {},
  "MVAU_hls_1": {
    "op_mac_4bx4b": 3650400,
    "param_weight_4b": 21600,
    "param_threshold_16b": 36
  },
  "ConvolutionInputGenerator_rtl_2": {},
  "MVAU_hls_2": {
    "op_mac_4bx4b": 1080000,
    "param_weight_4b": 43200,
    "param_threshold_16b": 48
  },
  "ConvolutionInputGenerator_rtl_3": {},
  "MVAU_hls_3": {
    "op_mac_4bx4b": 248832,
    "param_weight_4b": 27648,
    "param_threshold_15b": 64
  },
  "ConvolutionInputGenerator_rtl_4": {},
  "MVAU_hls_4": {
    "op_mac_4bx4b": 36864,
    "param_weight_4b": 36864,
    "param_threshold_16b": 64
  },
  "MVAU_hls_5": {
    "op_mac_4bx4b": 6400,
    "param_weight_4b": 6400,
    "param_threshold_13b": 100
  },
  "MVAU_hls_6": {
    "op_mac_4bx4b": 5000,
    "param_weight_4b": 5000,
    "param_threshold_13b": 50
  },
  "MVAU_hls_7": {
    "op_mac_4bx4b": 500,
    "param_weight_4b": 500,
    "param_threshold_12b": 10
  },
  "MVAU_rtl_0": {
    "op_mac_4bx4b": 10,
    "param_weight_4b": 10
  },
  "total": {
    "op_mac_4bx8b": 540000.0,
    "param_weight_4b": 141822.0,
    "param_threshold_16b": 172.0,
    "op_mac_4bx4b": 5028006.0,
    "param_threshold_15b": 64.0,
    "param_threshold_13b": 150.0,
    "param_threshold_12b": 10.0
  }
}